template_python_project/__init__.py
template_python_project/__main__.py
template_python_project/main.py
template_python_project/core/__init__.py
template_python_project/core/compute.py
template_python_project/core/concat.py
template_python_project/logging/__init__.py
template_python_project/logging/logger.py
tests/__init__.py
tests/functionnal/__init__.py
tests/functionnal/test_subcommand_compute.py
tests/functionnal/test_subcommand_concat.py
tests/unit/__init__.py
template_python_project-0.6.0.dist-info/LICENSE
template_python_project-0.6.0.dist-info/METADATA
template_python_project-0.6.0.dist-info/WHEEL
template_python_project-0.6.0.dist-info/entry_points.txt
template_python_project-0.6.0.dist-info/top_level.txt
template_python_project-0.6.0.dist-info/RECORD
