Metadata-Version: 2.1
Name: template-python-project
Version: 0.6.0
Summary: Template test for python bin
Home-page: https://github.com/ulphidius/template_python_project
Author: ulphidius
License: UNKNOWN
Platform: UNKNOWN
Requires-Dist: click (==7.1.2)
Provides-Extra: development
Requires-Dist: pytest (==6.2.2) ; extra == 'development'
Requires-Dist: pylint (==2.7.4) ; extra == 'development'
Requires-Dist: pytest-cov (==2.11.1) ; extra == 'development'
Requires-Dist: coveralls (==3.0.1) ; extra == 'development'
